html2text/__init__.py
html2text/__main__.py
html2text/cli.py
html2text/config.py
html2text/utils.py
html2text-2019.9.26.dist-info/AUTHORS.rst
html2text-2019.9.26.dist-info/COPYING
html2text-2019.9.26.dist-info/METADATA
html2text-2019.9.26.dist-info/WHEEL
html2text-2019.9.26.dist-info/entry_points.txt
html2text-2019.9.26.dist-info/top_level.txt
html2text-2019.9.26.dist-info/RECORD
